BLSSLIB/DecodeBlockItem.py
BLSSLIB/DecodeBlockSave.py
BLSSLIB/EncodeBlockItem.py
BLSSLIB/EncodeBlockSave.py
BLSSLIB/Ver.py
BLSSLIB/__init__.py
BLSSLIB/addEeprom.py
BLSSLIB/base64Decode.py
BLSSLIB/base64Encode.py
BLSSLIB/sharedInfo.py
BLSSLIB-0.1.18.dist-info/METADATA
BLSSLIB-0.1.18.dist-info/WHEEL
BLSSLIB-0.1.18.dist-info/top_level.txt
BLSSLIB-0.1.18.dist-info/RECORD
