Metadata-Version: 2.1
Name: BLSSLIB
Version: 0.1.18
Summary: A Python library for encoding and decoding Build logic save data.
Author: Back
License: GPL-3.0-or-later
Classifier: Programming Language :: Python :: 3
Classifier: License :: OSI Approved :: GNU General Public License v3 or later (GPLv3+)
Classifier: Operating System :: OS Independent
Requires-Python: >=3.6
